alpha_dbutility.pyd
alpha_error_code.pyd
alpha_quant.pyd
alpha_trade_client.pyd
alpha_update_client.pyd
alpha_utility.pyd
ctp_future_minutes_data_client.pyd
ctp_realtime_data_client.pyd
future_info_client.pyd
futures_history_client.pyd
futures_history_minutes_data_client.pyd
host_port_client_config.pyd
key_value_store.pyd
live_trade_system_client.pyd
realtime_data_client.pyd
static_price_adjust.pyd
stock_financials_client.pyd
stock_history_client.pyd
stock_list_client.pyd
stock_sharing_client.pyd
alpha_quant-1.6.dist-info/DESCRIPTION.rst
alpha_quant-1.6.dist-info/METADATA
alpha_quant-1.6.dist-info/RECORD
alpha_quant-1.6.dist-info/WHEEL
alpha_quant-1.6.dist-info/metadata.json
alpha_quant-1.6.dist-info/top_level.txt
alpha_trade/AlphaTrade.py
alpha_trade/__init__.py
alpha_trade/constants.py
alpha_trade/ttypes.py
