Metadata-Version: 2.0
Name: alpha-quant
Version: 1.6
Summary: Alpha Quant SDK
Home-page: http://www.alpha-qt.com
Author: http://www.alpha-qt.com
Author-email: UNKNOWN
License: LGPL
Platform: UNKNOWN
Requires-Dist: redis
Requires-Dist: thrift
